{ 
    "localfile": "Markham_City_Owned_Facilities (1).csv",
    "url":"",
    "format":"csv",
    "database_type": "library",
    "info": {
        "library_name": "Name",
        "library_type": "TYPE",
        "address_full": "ADDRESS",
        "longitude": "x",
        "latitude": "y",
        "file_type": "force:Mixed",
        "data_city": "force:Markham",
        "data_prov/terr": "force:ON",
        "data_provider": "force:Markham",
        "address_concat": "force: ",
         "address": {
            "city": "TOWNAREA"        }
    },
    "filter": {
         "DEPTRESP": "Culture"  
    }
}